{
    "date": "2017-09-22T11:59:20Z",
    "title": "Dotard or Rocket Man \u2013 who said what in the Trump v Kim Jong-un war of words?",
    "url": "https://www.theguardian.com/world/2017/sep/22/rocket-man-or-dotard-who-said-what-in-the-trump-v-kim-jong-un-war-of-words",
    "content": "With Kim Jong-un creatively bringing the word \u2018dotard\u2019 back into fashion in his response to Donald Trump\u2019s speech this week at the UN, here is a look at the insults the two have been exchanging throughout this year. Can you spot which phrases come from the mouth of an outspoken, unpredictable and dangerous leader, and which come from North Korea\u2019s Kim Jong-un?",
    "keywords": [
        "spot",
        "war",
        "man",
        "speech",
        "week",
        "kim",
        "come",
        "unpredictable",
        "trump",
        "jongun",
        "dotard",
        "words",
        "trumps",
        "response",
        "word",
        "rocket",
        "v"
    ],
    "summary": "With Kim Jong-un creatively bringing the word \u2018dotard\u2019 back into fashion in his response to Donald Trump\u2019s speech this week at the UN, here is a look at the insults the two have been exchanging throughout this year.\nCan you spot which phrases come from the mouth of an outspoken, unpredictable and dangerous leader, and which come from North Korea\u2019s Kim Jong-un?",
    "sentiment": {
        "neg": 0.094,
        "neu": 0.8745,
        "pos": 0.031,
        "compound": -0.277
    }
}